awslabs/__init__.py
awslabs/ccapi_mcp_server/__init__.py
awslabs/ccapi_mcp_server/aws_client.py
awslabs/ccapi_mcp_server/cloud_control_utils.py
awslabs/ccapi_mcp_server/context.py
awslabs/ccapi_mcp_server/errors.py
awslabs/ccapi_mcp_server/iac_generator.py
awslabs/ccapi_mcp_server/infrastructure_generator.py
awslabs/ccapi_mcp_server/schema_manager.py
awslabs/ccapi_mcp_server/server.py
awslabs/ccapi_mcp_server/impl/__init__.py
awslabs/ccapi_mcp_server/impl/tools/__init__.py
awslabs/ccapi_mcp_server/impl/tools/explanation.py
awslabs/ccapi_mcp_server/impl/tools/infrastructure_generation.py
awslabs/ccapi_mcp_server/impl/tools/resource_operations.py
awslabs/ccapi_mcp_server/impl/tools/security_scanning.py
awslabs/ccapi_mcp_server/impl/tools/session_management.py
awslabs/ccapi_mcp_server/impl/utils/__init__.py
awslabs/ccapi_mcp_server/impl/utils/validation.py
awslabs/ccapi_mcp_server/models/__init__.py
awslabs/ccapi_mcp_server/models/models.py
awslabs/ccapi_mcp_server/static/__init__.py
awslabs_ccapi_mcp_server-1.0.14.dist-info/METADATA
awslabs_ccapi_mcp_server-1.0.14.dist-info/WHEEL
awslabs_ccapi_mcp_server-1.0.14.dist-info/entry_points.txt
awslabs_ccapi_mcp_server-1.0.14.dist-info/licenses/LICENSE
awslabs_ccapi_mcp_server-1.0.14.dist-info/licenses/NOTICE
awslabs_ccapi_mcp_server-1.0.14.dist-info/RECORD
